TapTargetView-0.1.2.data/scripts/taptargetview.py
taptargetview/__init__.py
taptargetview/taptargetview.py
TapTargetView-0.1.2.dist-info/LICENSE
TapTargetView-0.1.2.dist-info/METADATA
TapTargetView-0.1.2.dist-info/WHEEL
TapTargetView-0.1.2.dist-info/top_level.txt
TapTargetView-0.1.2.dist-info/RECORD
