Metadata-Version: 2.1
Name: TapTargetView
Version: 0.1.2
Summary: Attempt to mimic Android's TapTargetView using Kivy and Python
Home-page: https://github.com/shashi278/TapTargetView
Author: Shashi Ranjan
Author-email: shashiranjankv@gmail.com
License: UNKNOWN
Keywords: Kivy Python TapTargetView
Platform: UNKNOWN
Classifier: Programming Language :: Python :: 3
Classifier: License :: OSI Approved :: MIT License
Classifier: Operating System :: OS Independent
Requires-Python: >=3.6
Requires-Dist: kivy
